cwl_wrapper/__init__.py
cwl_wrapper/app.py
cwl_wrapper/blender.py
cwl_wrapper/parser.py
cwl_wrapper/rulez.py
cwl_wrapper/utils.py
cwl_wrapper/workflow.py
cwl_wrapper/assets/maincwl.yaml
cwl_wrapper/assets/maincwlmetrics.yaml
cwl_wrapper/assets/rules.yaml
cwl_wrapper/assets/stagein.yaml
cwl_wrapper/assets/stageout.yaml
cwl_wrapper/cwl/__init__.py
cwl_wrapper/cwl/t2cwl.py
cwl_wrapper-0.12.3.dist-info/METADATA
cwl_wrapper-0.12.3.dist-info/WHEEL
cwl_wrapper-0.12.3.dist-info/entry_points.txt
cwl_wrapper-0.12.3.dist-info/licenses/LICENSE
cwl_wrapper-0.12.3.dist-info/RECORD
