Metadata-Version: 2.3
Name: cwl-wrapper
Version: 0.12.3
Summary: CWL wrapper to add stage-in and stage-out to a base app package
Project-URL: Documentation, https://github.com/EOEPCA/cwl-wrapper#readme
Project-URL: Issues, https://github.com/EOEPCA/cwl-wrapper/issues
Project-URL: Source, https://github.com/EOEPCA/cwl-wrapper
Author-email: Fabrice Brito <fabrice.brito@terradue.com>
License-Expression: Apache-2.0
License-File: LICENSE
Classifier: Development Status :: 4 - Beta
Classifier: Environment :: Console
Classifier: Intended Audience :: Developers
Classifier: Programming Language :: Python
Classifier: Programming Language :: Python :: Implementation :: PyPy
Requires-Dist: click
Requires-Dist: click-config-file
Requires-Dist: jinja2
Requires-Dist: loguru
Requires-Dist: pyyaml
Requires-Dist: setuptools
